pywpb/__init__.py
pywpb/pywpb.py
pywpb/templates/config_body.css
pywpb/templates/config_close.css
pywpb/templates/config_close_body.css
pywpb/templates/config_close_page.css
pywpb/templates/config_color_text.css
pywpb/templates/config_dlist.css
pywpb/templates/config_footer.css
pywpb/templates/config_form_sign_up.css
pywpb/templates/config_form_submit.css
pywpb/templates/config_frame.css
pywpb/templates/config_h.css
pywpb/templates/config_h_shadow.css
pywpb/templates/config_header.css
pywpb/templates/config_hline.css
pywpb/templates/config_image.css
pywpb/templates/config_logo.css
pywpb/templates/config_olist.css
pywpb/templates/config_page_header.css
pywpb/templates/config_sign_up.css
pywpb/templates/config_tab.css
pywpb/templates/config_tab.html
pywpb/templates/config_tab1.css
pywpb/templates/config_tab2.css
pywpb/templates/config_tab3.css
pywpb/templates/config_tab4.css
pywpb/templates/config_table_tbodyb.css
pywpb/templates/config_table_tbodyf.css
pywpb/templates/config_table_tbodyh.css
pywpb/templates/config_table_tfootb.css
pywpb/templates/config_table_tfootf.css
pywpb/templates/config_table_tfooth.css
pywpb/templates/config_table_theadb.css
pywpb/templates/config_table_theadf.css
pywpb/templates/config_table_theadh.css
pywpb/templates/config_tablef.css
pywpb/templates/config_tableh.css
pywpb/templates/config_ulist.css
pywpb/templates/config_video.css
pywpb/templates/config_youtube.css
pywpb/templates/templates.dat
pywpb-0.1.16.dist-info/METADATA
pywpb-0.1.16.dist-info/WHEEL
pywpb-0.1.16.dist-info/top_level.txt
pywpb-0.1.16.dist-info/RECORD
