Metadata-Version: 2.1
Name: pywpb
Version: 0.1.16
Summary: pyWPB - Python Web Page Builder
Home-page: https://github.com/dbranquinho/pywpb
Author: Delermando Branquinho Filho
Author-email: delermando@gmail.com
License: MIT
Platform: UNKNOWN
Requires-Dist: matplotlib (>=3.3.4)
Requires-Dist: numpy (>=1.19.2)
Requires-Dist: pandas (>=1.1.3)
Requires-Dist: seaborn (>=0.11.1)
Requires-Dist: utils (>=1.0.1)
